FLNetwork/__init__.py
FLNetwork/device.py
FLNetwork/paramServer.py
fl_network-1.0.2.dist-info/LICENSE
fl_network-1.0.2.dist-info/METADATA
fl_network-1.0.2.dist-info/WHEEL
fl_network-1.0.2.dist-info/top_level.txt
fl_network-1.0.2.dist-info/RECORD
