Metadata-Version: 2.1
Name: fl-network
Version: 1.0.2
Summary: Extensible network framework library for federated learning system
Home-page: https://github.com/Rostar-github/fedml-network
Author: Sida Luo
Author-email: luosida@qq.com
License: MIT
Keywords: FedML,Redis,Distribution
Platform: UNKNOWN
Classifier: License :: OSI Approved :: MIT License
Classifier: Operating System :: OS Independent
Classifier: Programming Language :: Python :: 3.8
Classifier: Programming Language :: Python :: 3.9
Classifier: Programming Language :: Python :: 3.10
Classifier: Programming Language :: Python :: 3.11
Classifier: Programming Language :: Python :: Implementation :: CPython
Classifier: Programming Language :: Python :: Implementation :: PyPy
Requires-Python: >=3.8
License-File: LICENSE
Requires-Dist: redis (>=4.2.2)
